[{"contributors": null, "truncated": false, "text": "#Repost webofedgar with repostapp\n\u30fb\u30fb\u30fb\nICYMI: thegirlonthetrainmovie #TheGirlOnTheTrain. Own it\u2026 https://t.co/A5KsUAck3C", "is_quote_status": false, "in_reply_to_status_id": null, "id": 801236329023434753, "favorite_count": 0, "entities": {"symbols": [], "user_mentions": [], "hashtags": [{"indices": [0, 7], "text": "Repost"}, {"indices": [68, 86], "text": "TheGirlOnTheTrain"}], "urls": [{"url": "https://t.co/A5KsUAck3C", "indices": [96, 119], "expanded_url": "https://www.instagram.com/p/BNIl9U6hP5R/", "display_url": "instagram.com/p/BNIl9U6hP5R/"}]}, "retweeted": false, "coordinates": null, "source": "<a href=\"http://instagram.com\" rel=\"nofollow\">Instagram</a>", "in_reply_to_screen_name": null, "in_reply_to_user_id": null, "retweet_count": 0, "id_str": "801236329023434753", "favorited": false, "user": {"follow_request_sent": false, "has_extended_profile": true, "profile_use_background_image": true, "default_profile_image": false, "id": 349246948, "profile_background_image_url_https": "https://pbs.twimg.com/profile_background_images/689327355/10c5118d0ca4b66b1c058288fe58cf73.jpeg", "verified": false, "translator_type": "none", "profile_text_color": "1B4205", "profile_image_url_https": "https://pbs.twimg.com/profile_images/478560673140842496/TPE_zWkc_normal.jpeg", "profile_sidebar_fill_color": "DDEEF6", "entities": {"url": {"urls": [{"url": "http://t.co/6CFBFgZjql", "indices": [0, 22], "expanded_url": "http://www.rafaeluribeochoa.blogspot.com", "display_url": "rafaeluribeochoa.blogspot.com"}]}, "description": {"urls": [{"url": "http://t.co/It6WkaZKpw", "indices": [30, 52], "expanded_url": "http://www.cfrepresentaciones.com/vcsys/", "display_url": "cfrepresentaciones.com/vcsys/"}]}}, "followers_count": 16189, "profile_sidebar_border_color": "FFFFFF", "id_str": "349246948", "profile_background_color": "F2F5F7", "listed_count": 53, "is_translation_enabled": false, "utc_offset": -18000, "statuses_count": 78896, "description": "SALVADO POR LOS PERROS ,ACTOR http://t.co/It6WkaZKpw. FUNDACION GRANESPIRITU", "friends_count": 2411, "location": "EN MANOS DEL GRAN ESPIRITU", "profile_link_color": "2A570C", "profile_image_url": "http://pbs.twimg.com/profile_images/478560673140842496/TPE_zWkc_normal.jpeg", "following": false, "geo_enabled": true, "profile_banner_url": "https://pbs.twimg.com/profile_banners/349246948/1403200873", "profile_background_image_url": "http://pbs.twimg.com/profile_background_images/689327355/10c5118d0ca4b66b1c058288fe58cf73.jpeg", "screen_name": "RAFAELURIBE8a", "lang": "es", "profile_background_tile": true, "favourites_count": 13835, "name": "RAFAEL URIBE OCHOA\u262e", "notifications": false, "url": "http://t.co/6CFBFgZjql", "created_at": "Fri Aug 05 20:08:05 +0000 2011", "contributors_enabled": false, "time_zone": "Bogota", "protected": false, "default_profile": false, "is_translator": false}, "geo": null, "in_reply_to_user_id_str": null, "possibly_sensitive": false, "lang": "en", "created_at": "Wed Nov 23 01:30:01 +0000 2016", "in_reply_to_status_id_str": null, "place": null, "metadata": {"iso_language_code": "en", "result_type": "recent"}}, {"contributors": null, "truncated": false, "text": "The happiness continues... #thegirlonthetrain #veuveclicquot #grouper @ Hot Fish Club https://t.co/BY5rFFxRtK", "is_quote_status": false, "in_reply_to_status_id": null, "id": 801235357396336640, "favorite_count": 0, "entities": {"symbols": [], "user_mentions": [], "hashtags": [{"indices": [27, 45], "text": "thegirlonthetrain"}, {"indices": [46, 60], "text": "veuveclicquot"}, {"indices": [61, 69], "text": "grouper"}], "urls": [{"url": "https://t.co/BY5rFFxRtK", "indices": [86, 109], "expanded_url": "https://www.instagram.com/p/BNIlhP_g-RT/", "display_url": "instagram.com/p/BNIlhP_g-RT/"}]}, "retweeted": false, "coordinates": {"type": "Point", "coordinates": [-79.0503731, 33.53945144]}, "source": "<a href=\"http://instagram.com\" rel=\"nofollow\">Instagram</a>", "in_reply_to_screen_name": null, "in_reply_to_user_id": null, "retweet_count": 0, "id_str": "801235357396336640", "favorited": false, "user": {"follow_request_sent": false, "has_extended_profile": false, "profile_use_background_image": true, "default_profile_image": false, "id": 200298221, "profile_background_image_url_https": "https://pbs.twimg.com/profile_background_images/530554848400252928/B0uNFhc_.jpeg", "verified": false, "translator_type": "none", "profile_text_color": "333333", "profile_image_url_https": "https://pbs.twimg.com/profile_images/2182926735/Jackiebw_edit_normal.jpg", "profile_sidebar_fill_color": "ACC56B", "entities": {"url": {"urls": [{"url": "http://t.co/462P4q7jvy", "indices": [0, 22], "expanded_url": "http://table6productions.com", "display_url": "table6productions.com"}]}, "description": {"urls": []}}, "followers_count": 651, "profile_sidebar_border_color": "FFFFFF", "id_str": "200298221", "profile_background_color": "FFFFFF", "listed_count": 17, "is_translation_enabled": false, "utc_offset": -18000, "statuses_count": 974, "description": "A few of my favorite things... banana pudding, rose gold, Paige jeans, Blink-182, Bewitched reruns, Audrey Hepburn, Chicago and eating breakfast for dinner!", "friends_count": 489, "location": "Tampa Bay", "profile_link_color": "D84D99", "profile_image_url": "http://pbs.twimg.com/profile_images/2182926735/Jackiebw_edit_normal.jpg", "following": false, "geo_enabled": true, "profile_banner_url": "https://pbs.twimg.com/profile_banners/200298221/1392006448", "profile_background_image_url": "http://pbs.twimg.com/profile_background_images/530554848400252928/B0uNFhc_.jpeg", "screen_name": "Table6Jackie", "lang": "en", "profile_background_tile": true, "favourites_count": 54, "name": "Jackie Ross", "notifications": false, "url": "http://t.co/462P4q7jvy", "created_at": "Fri Oct 08 23:19:04 +0000 2010", "contributors_enabled": false, "time_zone": "Eastern Time (US & Canada)", "protected": false, "default_profile": false, "is_translator": false}, "geo": {"type": "Point", "coordinates": [33.53945144, -79.0503731]}, "in_reply_to_user_id_str": null, "possibly_sensitive": false, "lang": "en", "created_at": "Wed Nov 23 01:26:10 +0000 2016", "in_reply_to_status_id_str": null, "place": {"full_name": "Murrells Inlet, SC", "url": "https://api.twitter.com/1.1/geo/id/f5d9845d07a82c46.json", "country": "United States", "place_type": "city", "bounding_box": {"type": "Polygon", "coordinates": [[[-79.087697, 33.523442], [-79.016701, 33.523442], [-79.016701, 33.572178], [-79.087697, 33.572178]]]}, "contained_within": [], "country_code": "US", "attributes": {}, "id": "f5d9845d07a82c46", "name": "Murrells Inlet"}, "metadata": {"iso_language_code": "en", "result_type": "recent"}}, {"contributors": null, "truncated": true, "text": "ICYMI: #TheGirlOnTheTrain. Own it with Deleted and Extended Scenes on Digital HD 1/3 and Blu-ray &amp; DVD 1/17\u2026 https://t.co/7JG9GpjLCA", "is_quote_status": false, "in_reply_to_status_id": null, "id": 801234301383802880, "favorite_count": 0, "entities": {"symbols": [], "user_mentions": [], "hashtags": [{"indices": [7, 25], "text": "TheGirlOnTheTrain"}], "urls": [{"url": "https://t.co/7JG9GpjLCA", "indices": [113, 136], "expanded_url": "https://twitter.com/i/web/status/801234301383802880", "display_url": "twitter.com/i/web/status/8\u2026"}]}, "retweeted": false, "coordinates": null, "source": "<a href=\"http://twitter.com/download/iphone\" rel=\"nofollow\">Twitter for iPhone</a>", "in_reply_to_screen_name": null, "in_reply_to_user_id": null, "retweet_count": 0, "id_str": "801234301383802880", "favorited": false, "user": {"follow_request_sent": false, "has_extended_profile": true, "profile_use_background_image": true, "default_profile_image": false, "id": 226712791, "profile_background_image_url_https": "https://pbs.twimg.com/profile_background_images/378800000168859622/EW6n7c8F.jpeg", "verified": false, "translator_type": "none", "profile_text_color": "575757", "profile_image_url_https": "https://pbs.twimg.com/profile_images/782765861157371904/6ECXNEq0_normal.jpg", "profile_sidebar_fill_color": "252429", "entities": {"url": {"urls": [{"url": "https://t.co/X7A5GndIWt", "indices": [0, 23], "expanded_url": "http://wp.me/7HfG", "display_url": "wp.me/7HfG"}]}, "description": {"urls": []}}, "followers_count": 5169, "profile_sidebar_border_color": "FFFFFF", "id_str": "226712791", "profile_background_color": "BFBBBF", "listed_count": 39, "is_translation_enabled": false, "utc_offset": -18000, "statuses_count": 9709, "description": "Welcome Official Twitter WEBSITE @EdgarRamirez25 YOUR #1 SOURCE. ISG & Snapchat: Edgarramirez25 | ISG & Snapchat FB: WebofEdgar | \u00a9WER @Maxdil & @lexarod |", "friends_count": 3511, "location": "Co,Vzla,Eur,Eua,Arg,Pty,Ita", "profile_link_color": "ABB8C2", "profile_image_url": "http://pbs.twimg.com/profile_images/782765861157371904/6ECXNEq0_normal.jpg", "following": false, "geo_enabled": false, "profile_banner_url": "https://pbs.twimg.com/profile_banners/226712791/1475461413", "profile_background_image_url": "http://pbs.twimg.com/profile_background_images/378800000168859622/EW6n7c8F.jpeg", "screen_name": "WebofEdgar", "lang": "en", "profile_background_tile": false, "favourites_count": 11941, "name": "Web Edgar Ram\u00edrez\u00ae", "notifications": false, "url": "https://t.co/X7A5GndIWt", "created_at": "Tue Dec 14 21:52:21 +0000 2010", "contributors_enabled": false, "time_zone": "Bogota", "protected": false, "default_profile": false, "is_translator": false}, "geo": null, "in_reply_to_user_id_str": null, "possibly_sensitive": false, "lang": "en", "created_at": "Wed Nov 23 01:21:58 +0000 2016", "in_reply_to_status_id_str": null, "place": null, "metadata": {"iso_language_code": "en", "result_type": "recent"}}, {"contributors": null, "truncated": false, "text": "#BooksIOwn #TheGirlOnTheTrain by @PaulaHWrites. A book that kept me awake at night.\u2026 https://t.co/HIV7L6b66w https://t.co/LlZKlQsZx1", "is_quote_status": false, "in_reply_to_status_id": null, "id": 801234234891501568, "favorite_count": 0, "entities": {"symbols": [], "user_mentions": [{"id": 50238695, "indices": [33, 46], "id_str": "50238695", "screen_name": "PaulaHWrites", "name": "Paula Hawkins"}], "hashtags": [{"indices": [0, 10], "text": "BooksIOwn"}, {"indices": [11, 29], "text": "TheGirlOnTheTrain"}], "urls": [{"url": "https://t.co/HIV7L6b66w", "indices": [85, 108], "expanded_url": "http://reginafoo.com/queenofbibliophile/2016/11/books-i-own-the-girl-on-the-train/", "display_url": "reginafoo.com/queenofbibliop\u2026"}], "media": [{"expanded_url": "https://twitter.com/queenofbiblio/status/801234234891501568/photo/1", "display_url": "pic.twitter.com/LlZKlQsZx1", "url": "https://t.co/LlZKlQsZx1", "media_url_https": "https://pbs.twimg.com/media/Cx6OSg7UcAEwqAo.jpg", "id_str": "801234232446054401", "sizes": {"small": {"h": 680, "resize": "fit", "w": 680}, "large": {"h": 896, "resize": "fit", "w": 896}, "medium": {"h": 896, "resize": "fit", "w": 896}, "thumb": {"h": 150, "resize": "crop", "w": 150}}, "indices": [109, 132], "type": "photo", "id": 801234232446054401, "media_url": "http://pbs.twimg.com/media/Cx6OSg7UcAEwqAo.jpg"}]}, "retweeted": false, "coordinates": null, "source": "<a href=\"http://publicize.wp.com/\" rel=\"nofollow\">WordPress.com</a>", "in_reply_to_screen_name": null, "in_reply_to_user_id": null, "retweet_count": 0, "id_str": "801234234891501568", "favorited": false, "user": {"follow_request_sent": false, "has_extended_profile": true, "profile_use_background_image": true, "default_profile_image": false, "id": 1440995922, "profile_background_image_url_https": "https://abs.twimg.com/images/themes/theme1/bg.png", "verified": false, "translator_type": "none", "profile_text_color": "333333", "profile_image_url_https": "https://pbs.twimg.com/profile_images/634928229095112704/c3IgpaoQ_normal.png", "profile_sidebar_fill_color": "DDEEF6", "entities": {"url": {"urls": [{"url": "https://t.co/9v9DHrZvys", "indices": [0, 23], "expanded_url": "http://reginafoo.com/queenofbibliophile", "display_url": "reginafoo.com/queenofbibliop\u2026"}]}, "description": {"urls": []}}, "followers_count": 567, "profile_sidebar_border_color": "C0DEED", "id_str": "1440995922", "profile_background_color": "C0DEED", "listed_count": 32, "is_translation_enabled": true, "utc_offset": 28800, "statuses_count": 5956, "description": "An ex-bookseller who still reads YA (a lot).", "friends_count": 324, "location": "Malaysia", "profile_link_color": "3B94D9", "profile_image_url": "http://pbs.twimg.com/profile_images/634928229095112704/c3IgpaoQ_normal.png", "following": false, "geo_enabled": true, "profile_banner_url": "https://pbs.twimg.com/profile_banners/1440995922/1419673422", "profile_background_image_url": "http://abs.twimg.com/images/themes/theme1/bg.png", "screen_name": "queenofbiblio", "lang": "en", "profile_background_tile": false, "favourites_count": 2140, "name": "Queen of Bibliophile", "notifications": false, "url": "https://t.co/9v9DHrZvys", "created_at": "Sun May 19 12:08:36 +0000 2013", "contributors_enabled": false, "time_zone": "Kuala Lumpur", "protected": false, "default_profile": false, "is_translator": false}, "geo": null, "in_reply_to_user_id_str": null, "possibly_sensitive": false, "lang": "en", "created_at": "Wed Nov 23 01:21:42 +0000 2016", "in_reply_to_status_id_str": null, "place": null, "extended_entities": {"media": [{"expanded_url": "https://twitter.com/queenofbiblio/status/801234234891501568/photo/1", "display_url": "pic.twitter.com/LlZKlQsZx1", "url": "https://t.co/LlZKlQsZx1", "media_url_https": "https://pbs.twimg.com/media/Cx6OSg7UcAEwqAo.jpg", "id_str": "801234232446054401", "sizes": {"small": {"h": 680, "resize": "fit", "w": 680}, "large": {"h": 896, "resize": "fit", "w": 896}, "medium": {"h": 896, "resize": "fit", "w": 896}, "thumb": {"h": 150, "resize": "crop", "w": 150}}, "indices": [109, 132], "type": "photo", "id": 801234232446054401, "media_url": "http://pbs.twimg.com/media/Cx6OSg7UcAEwqAo.jpg"}]}, "metadata": {"iso_language_code": "en", "result_type": "recent"}}, {"contributors": null, "truncated": false, "text": "Why are You here?!\n#TheGirlOnTheTrain https://t.co/mepe0QiPnf", "is_quote_status": false, "in_reply_to_status_id": null, "id": 801222753089097728, "favorite_count": 0, "entities": {"symbols": [], "user_mentions": [], "hashtags": [{"indices": [19, 37], "text": "TheGirlOnTheTrain"}], "urls": [], "media": [{"expanded_url": "https://twitter.com/hana_egy2/status/801222753089097728/photo/1", "display_url": "pic.twitter.com/mepe0QiPnf", "url": "https://t.co/mepe0QiPnf", "media_url_https": "https://pbs.twimg.com/tweet_video_thumb/Cx6DGbAWIAA2QvA.jpg", "id_str": "801221930070188032", "sizes": {"large": {"h": 268, "resize": "fit", "w": 500}, "small": {"h": 182, "resize": "fit", "w": 340}, "medium": {"h": 268, "resize": "fit", "w": 500}, "thumb": {"h": 150, "resize": "crop", "w": 150}}, "indices": [38, 61], "type": "photo", "id": 801221930070188032, "media_url": "http://pbs.twimg.com/tweet_video_thumb/Cx6DGbAWIAA2QvA.jpg"}]}, "retweeted": false, "coordinates": null, "source": "<a href=\"http://twitter.com/download/android\" rel=\"nofollow\">Twitter for Android</a>", "in_reply_to_screen_name": null, "in_reply_to_user_id": null, "retweet_count": 0, "id_str": "801222753089097728", "favorited": false, "user": {"follow_request_sent": false, "has_extended_profile": true, "profile_use_background_image": true, "default_profile_image": false, "id": 451229242, "profile_background_image_url_https": "https://abs.twimg.com/images/themes/theme14/bg.gif", "verified": false, "translator_type": "none", "profile_text_color": "333333", "profile_image_url_https": "https://pbs.twimg.com/profile_images/799818852687286272/7s88Lmzi_normal.jpg", "profile_sidebar_fill_color": "EFEFEF", "entities": {"description": {"urls": []}}, "followers_count": 196, "profile_sidebar_border_color": "FFFFFF", "id_str": "451229242", "profile_background_color": "FF6699", "listed_count": 8, "is_translation_enabled": false, "utc_offset": 7200, "statuses_count": 5515, "description": "\u200f\u200f\u200f\u200f\u200f\u200f\u200f\u200f\u200f\u200f\u200f\u200f\u200f\u200f\u200f\u200f\u200f\u200f\u200f\u200f\u200f\u200f\u200f\u200f\u200f\u200f\u200f\u200f\u0642\u062f \u0644\u0627 \u0627\u0631\u0627\u0643..\u0644\u0643\u0646 \u0645\u0627\u0632\u0644\u062a \u0627\u0634\u0639\u0631 \u0628\u0643\u2764\nSophomore\u270c", "friends_count": 149, "location": "Cairo, Egypt", "profile_link_color": "F58EA8", "profile_image_url": "http://pbs.twimg.com/profile_images/799818852687286272/7s88Lmzi_normal.jpg", "following": false, "geo_enabled": false, "profile_banner_url": "https://pbs.twimg.com/profile_banners/451229242/1479526650", "profile_background_image_url": "http://abs.twimg.com/images/themes/theme14/bg.gif", "screen_name": "hana_egy2", "lang": "en", "profile_background_tile": true, "favourites_count": 3084, "name": "HANA", "notifications": false, "url": null, "created_at": "Sat Dec 31 05:46:46 +0000 2011", "contributors_enabled": false, "time_zone": "Cairo", "protected": false, "default_profile": false, "is_translator": false}, "geo": null, "in_reply_to_user_id_str": null, "possibly_sensitive": true, "lang": "en", "created_at": "Wed Nov 23 00:36:04 +0000 2016", "in_reply_to_status_id_str": null, "place": null, "extended_entities": {"media": [{"expanded_url": "https://twitter.com/hana_egy2/status/801222753089097728/photo/1", "display_url": "pic.twitter.com/mepe0QiPnf", "url": "https://t.co/mepe0QiPnf", "media_url_https": "https://pbs.twimg.com/tweet_video_thumb/Cx6DGbAWIAA2QvA.jpg", "video_info": {"aspect_ratio": [125, 67], "variants": [{"url": "https://pbs.twimg.com/tweet_video/Cx6DGbAWIAA2QvA.mp4", "bitrate": 0, "content_type": "video/mp4"}]}, "id_str": "801221930070188032", "sizes": {"large": {"h": 268, "resize": "fit", "w": 500}, "small": {"h": 182, "resize": "fit", "w": 340}, "medium": {"h": 268, "resize": "fit", "w": 500}, "thumb": {"h": 150, "resize": "crop", "w": 150}}, "indices": [38, 61], "type": "animated_gif", "id": 801221930070188032, "media_url": "http://pbs.twimg.com/tweet_video_thumb/Cx6DGbAWIAA2QvA.jpg"}]}, "metadata": {"iso_language_code": "en", "result_type": "recent"}}, {"contributors": null, "truncated": false, "text": "@PaulaHWrites Paula, I was given #TheGirlOnTheTrain 2 read &amp; promised I'd love it &amp; I did! Read it in 3 evenings, couldn't put it down! Fab!", "is_quote_status": false, "in_reply_to_status_id": null, "id": 801207139742183424, "favorite_count": 0, "entities": {"symbols": [], "user_mentions": [{"id": 50238695, "indices": [0, 13], "id_str": "50238695", "screen_name": "PaulaHWrites", "name": "Paula Hawkins"}], "hashtags": [{"indices": [33, 51], "text": "TheGirlOnTheTrain"}], "urls": []}, "retweeted": false, "coordinates": null, "source": "<a href=\"http://twitter.com/download/iphone\" rel=\"nofollow\">Twitter for iPhone</a>", "in_reply_to_screen_name": "PaulaHWrites", "in_reply_to_user_id": 50238695, "retweet_count": 0, "id_str": "801207139742183424", "favorited": false, "user": {"follow_request_sent": false, "has_extended_profile": true, "profile_use_background_image": true, "default_profile_image": false, "id": 310510927, "profile_background_image_url_https": "https://abs.twimg.com/images/themes/theme1/bg.png", "verified": false, "translator_type": "none", "profile_text_color": "333333", "profile_image_url_https": "https://pbs.twimg.com/profile_images/590595423355727874/f8xyAgPt_normal.jpg", "profile_sidebar_fill_color": "DDEEF6", "entities": {"description": {"urls": []}}, "followers_count": 67, "profile_sidebar_border_color": "C0DEED", "id_str": "310510927", "profile_background_color": "C0DEED", "listed_count": 1, "is_translation_enabled": false, "utc_offset": null, "statuses_count": 454, "description": "", "friends_count": 434, "location": "Lichfield, Staffordshire ", "profile_link_color": "1DA1F2", "profile_image_url": "http://pbs.twimg.com/profile_images/590595423355727874/f8xyAgPt_normal.jpg", "following": false, "geo_enabled": true, "profile_banner_url": "https://pbs.twimg.com/profile_banners/310510927/1348782449", "profile_background_image_url": "http://abs.twimg.com/images/themes/theme1/bg.png", "screen_name": "gurl_amy", "lang": "en", "profile_background_tile": false, "favourites_count": 1093, "name": "Amy", "notifications": false, "url": null, "created_at": "Fri Jun 03 21:43:50 +0000 2011", "contributors_enabled": false, "time_zone": null, "protected": false, "default_profile": true, "is_translator": false}, "geo": null, "in_reply_to_user_id_str": "50238695", "lang": "en", "created_at": "Tue Nov 22 23:34:02 +0000 2016", "in_reply_to_status_id_str": null, "place": null, "metadata": {"iso_language_code": "en", "result_type": "recent"}}, {"contributors": null, "truncated": false, "text": "RT @sttepodcast: On our new episode we will be reviewing #TheGirlOnTheTrain and our rewatch is Four Lions. New #podcast out tomorrow #SkipT\u2026", "is_quote_status": false, "in_reply_to_status_id": null, "id": 801207038109974528, "favorite_count": 0, "entities": {"symbols": [], "user_mentions": [{"id": 2709128076, "indices": [3, 15], "id_str": "2709128076", "screen_name": "sttepodcast", "name": "Skip To The End"}], "hashtags": [{"indices": [57, 75], "text": "TheGirlOnTheTrain"}, {"indices": [111, 119], "text": "podcast"}], "urls": []}, "retweeted": false, "coordinates": null, "source": "<a href=\"http://twitter.com\" rel=\"nofollow\">Twitter Web Client</a>", "in_reply_to_screen_name": null, "in_reply_to_user_id": null, "retweet_count": 7, "id_str": "801207038109974528", "favorited": false, "retweeted_status": {"contributors": null, "truncated": true, "text": "On our new episode we will be reviewing #TheGirlOnTheTrain and our rewatch is Four Lions. New #podcast out tomorrow\u2026 https://t.co/NG72IHQFER", "is_quote_status": false, "in_reply_to_status_id": null, "id": 786873630592499712, "favorite_count": 13, "entities": {"symbols": [], "user_mentions": [], "hashtags": [{"indices": [40, 58], "text": "TheGirlOnTheTrain"}, {"indices": [94, 102], "text": "podcast"}], "urls": [{"url": "https://t.co/NG72IHQFER", "indices": [117, 140], "expanded_url": "https://twitter.com/i/web/status/786873630592499712", "display_url": "twitter.com/i/web/status/7\u2026"}]}, "retweeted": false, "coordinates": null, "source": "<a href=\"http://twitter.com/download/iphone\" rel=\"nofollow\">Twitter for iPhone</a>", "in_reply_to_screen_name": null, "in_reply_to_user_id": null, "retweet_count": 7, "id_str": "786873630592499712", "favorited": false, "user": {"follow_request_sent": false, "has_extended_profile": false, "profile_use_background_image": true, "default_profile_image": false, "id": 2709128076, "profile_background_image_url_https": "https://abs.twimg.com/images/themes/theme1/bg.png", "verified": false, "translator_type": "none", "profile_text_color": "333333", "profile_image_url_https": "https://pbs.twimg.com/profile_images/761926384990191616/D0A4JSfM_normal.jpg", "profile_sidebar_fill_color": "DDEEF6", "entities": {"url": {"urls": [{"url": "https://t.co/6JisfUEXtn", "indices": [0, 23], "expanded_url": "http://skiptotheend.co.uk", "display_url": "skiptotheend.co.uk"}]}, "description": {"urls": [{"url": "https://t.co/WtbjlvAsLL", "indices": [71, 94], "expanded_url": "http://skiptotheend.podomatic.com", "display_url": "skiptotheend.podomatic.com"}, {"url": "https://t.co/FZ7lbqdAHh", "indices": [96, 119], "expanded_url": "http://Instagram.com/skiptotheendpodcast", "display_url": "Instagram.com/skiptotheendpo\u2026"}]}}, "followers_count": 40274, "profile_sidebar_border_color": "C0DEED", "id_str": "2709128076", "profile_background_color": "C0DEED", "listed_count": 376, "is_translation_enabled": false, "utc_offset": 0, "statuses_count": 12378, "description": "A movies podcast with Mark, Ben & Gemma. Find us on iTunes, Stitcher & https://t.co/WtbjlvAsLL. https://t.co/FZ7lbqdAHh", "friends_count": 19234, "location": "Location : The Cinema", "profile_link_color": "1DA1F2", "profile_image_url": "http://pbs.twimg.com/profile_images/761926384990191616/D0A4JSfM_normal.jpg", "following": false, "geo_enabled": false, "profile_banner_url": "https://pbs.twimg.com/profile_banners/2709128076/1470431278", "profile_background_image_url": "http://abs.twimg.com/images/themes/theme1/bg.png", "screen_name": "sttepodcast", "lang": "en", "profile_background_tile": false, "favourites_count": 19435, "name": "Skip To The End", "notifications": false, "url": "https://t.co/6JisfUEXtn", "created_at": "Tue Aug 05 12:04:39 +0000 2014", "contributors_enabled": false, "time_zone": "Dublin", "protected": false, "default_profile": true, "is_translator": false}, "geo": null, "in_reply_to_user_id_str": null, "possibly_sensitive": false, "lang": "en", "created_at": "Fri Oct 14 10:17:47 +0000 2016", "in_reply_to_status_id_str": null, "place": null, "metadata": {"iso_language_code": "en", "result_type": "recent"}}, "user": {"follow_request_sent": false, "has_extended_profile": false, "profile_use_background_image": true, "default_profile_image": false, "id": 783436002081837060, "profile_background_image_url_https": null, "verified": false, "translator_type": "none", "profile_text_color": "333333", "profile_image_url_https": "https://pbs.twimg.com/profile_images/784765061562830848/V_9jWcTk_normal.jpg", "profile_sidebar_fill_color": "DDEEF6", "entities": {"description": {"urls": []}}, "followers_count": 31, "profile_sidebar_border_color": "C0DEED", "id_str": "783436002081837060", "profile_background_color": "F5F8FA", "listed_count": 2, "is_translation_enabled": false, "utc_offset": null, "statuses_count": 433, "description": "", "friends_count": 389, "location": "", "profile_link_color": "1DA1F2", "profile_image_url": "http://pbs.twimg.com/profile_images/784765061562830848/V_9jWcTk_normal.jpg", "following": false, "geo_enabled": false, "profile_background_image_url": null, "screen_name": "avadesimpsonze1", "lang": "ru", "profile_background_tile": false, "favourites_count": 1461, "name": "Penelope Watson", "notifications": false, "url": null, "created_at": "Tue Oct 04 22:37:53 +0000 2016", "contributors_enabled": false, "time_zone": null, "protected": false, "default_profile": true, "is_translator": false}, "geo": null, "in_reply_to_user_id_str": null, "lang": "en", "created_at": "Tue Nov 22 23:33:38 +0000 2016", "in_reply_to_status_id_str": null, "place": null, "metadata": {"iso_language_code": "en", "result_type": "recent"}}, {"contributors": null, "truncated": false, "text": "#TheGirlOnTheTrain - Gripping, enthralling - a top-notch thriller and a compulsive read - https://t.co/lj52sFAt0B", "is_quote_status": false, "in_reply_to_status_id": null, "id": 801185955508080640, "favorite_count": 0, "entities": {"symbols": [], "user_mentions": [], "hashtags": [{"indices": [0, 18], "text": "TheGirlOnTheTrain"}], "urls": [{"url": "https://t.co/lj52sFAt0B", "indices": [90, 113], "expanded_url": "http://bit.ly/kindleprizes3", "display_url": "bit.ly/kindleprizes3"}]}, "retweeted": false, "coordinates": null, "source": "<a href=\"http://twitter.com\" rel=\"nofollow\">Twitter Web Client</a>", "in_reply_to_screen_name": null, "in_reply_to_user_id": null, "retweet_count": 0, "id_str": "801185955508080640", "favorited": false, "user": {"follow_request_sent": false, "has_extended_profile": false, "profile_use_background_image": true, "default_profile_image": false, "id": 4909252631, "profile_background_image_url_https": null, "verified": false, "translator_type": "none", "profile_text_color": "333333", "profile_image_url_https": "https://pbs.twimg.com/profile_images/698888608502177792/PHwDrjzq_normal.jpg", "profile_sidebar_fill_color": "DDEEF6", "entities": {"description": {"urls": []}}, "followers_count": 5068, "profile_sidebar_border_color": "C0DEED", "id_str": "4909252631", "profile_background_color": "F5F8FA", "listed_count": 124, "is_translation_enabled": false, "utc_offset": null, "statuses_count": 23992, "description": "#Kindle #Prizes & updates on the latest #books and #offers in the #UK", "friends_count": 4218, "location": "United Kingdom", "profile_link_color": "1DA1F2", "profile_image_url": "http://pbs.twimg.com/profile_images/698888608502177792/PHwDrjzq_normal.jpg", "following": false, "geo_enabled": false, "profile_banner_url": "https://pbs.twimg.com/profile_banners/4909252631/1455463381", "profile_background_image_url": null, "screen_name": "KindlePrizes", "lang": "en-gb", "profile_background_tile": false, "favourites_count": 1, "name": "Kindle Prizes", "notifications": false, "url": null, "created_at": "Sun Feb 14 14:54:13 +0000 2016", "contributors_enabled": false, "time_zone": null, "protected": false, "default_profile": true, "is_translator": false}, "geo": null, "in_reply_to_user_id_str": null, "possibly_sensitive": false, "lang": "en", "created_at": "Tue Nov 22 22:09:51 +0000 2016", "in_reply_to_status_id_str": null, "place": null, "metadata": {"iso_language_code": "en", "result_type": "recent"}}, {"contributors": null, "truncated": false, "text": "I see it. Exceptional, unlimited beauty, my dear Emily &lt;3 #TheGirlOnTheTrain #NowWatching https://t.co/X5BRQTDRm4", "is_quote_status": false, "in_reply_to_status_id": null, "id": 801174211595120644, "favorite_count": 0, "entities": {"symbols": [], "user_mentions": [], "hashtags": [{"indices": [61, 79], "text": "TheGirlOnTheTrain"}, {"indices": [80, 92], "text": "NowWatching"}], "urls": [], "media": [{"expanded_url": "https://twitter.com/marincuric/status/801174211595120644/photo/1", "display_url": "pic.twitter.com/X5BRQTDRm4", "url": "https://t.co/X5BRQTDRm4", "media_url_https": "https://pbs.twimg.com/media/Cx5XbbyXgAAhnVZ.jpg", "id_str": "801173912545624064", "sizes": {"large": {"h": 667, "resize": "fit", "w": 1351}, "small": {"h": 336, "resize": "fit", "w": 680}, "medium": {"h": 592, "resize": "fit", "w": 1200}, "thumb": {"h": 150, "resize": "crop", "w": 150}}, "indices": [93, 116], "type": "photo", "id": 801173912545624064, "media_url": "http://pbs.twimg.com/media/Cx5XbbyXgAAhnVZ.jpg"}]}, "retweeted": false, "coordinates": null, "source": "<a href=\"http://twitter.com\" rel=\"nofollow\">Twitter Web Client</a>", "in_reply_to_screen_name": null, "in_reply_to_user_id": null, "retweet_count": 0, "id_str": "801174211595120644", "favorited": false, "user": {"follow_request_sent": false, "has_extended_profile": true, "profile_use_background_image": false, "default_profile_image": false, "id": 40715019, "profile_background_image_url_https": "https://abs.twimg.com/images/themes/theme17/bg.gif", "verified": false, "translator_type": "none", "profile_text_color": "000000", "profile_image_url_https": "https://pbs.twimg.com/profile_images/785208587345915905/fovN_iFT_normal.jpg", "profile_sidebar_fill_color": "000000", "entities": {"url": {"urls": [{"url": "https://t.co/I2UGPzmeMZ", "indices": [0, 23], "expanded_url": "http://hr.linkedin.com/pub/marin-curic/5a/aa0/21b", "display_url": "hr.linkedin.com/pub/marin-curi\u2026"}]}, "description": {"urls": []}}, "followers_count": 5537, "profile_sidebar_border_color": "000000", "id_str": "40715019", "profile_background_color": "000000", "listed_count": 64, "is_translation_enabled": false, "utc_offset": 3600, "statuses_count": 17337, "description": "TV journo @STVOsijek  #media #politics  #PR #music #travel #Croatia #ideas  #goodreads #innovation #design random stuff. Views  my own. PG rated #teamblackberry", "friends_count": 204, "location": "Worldwide, Croatia", "profile_link_color": "000000", "profile_image_url": "http://pbs.twimg.com/profile_images/785208587345915905/fovN_iFT_normal.jpg", "following": false, "geo_enabled": false, "profile_banner_url": "https://pbs.twimg.com/profile_banners/40715019/1478692025", "profile_background_image_url": "http://abs.twimg.com/images/themes/theme17/bg.gif", "screen_name": "marincuric", "lang": "en", "profile_background_tile": false, "favourites_count": 572, "name": "Marin Curic", "notifications": false, "url": "https://t.co/I2UGPzmeMZ", "created_at": "Sun May 17 19:03:21 +0000 2009", "contributors_enabled": false, "time_zone": "Zagreb", "protected": false, "default_profile": false, "is_translator": false}, "geo": null, "in_reply_to_user_id_str": null, "possibly_sensitive": false, "lang": "en", "created_at": "Tue Nov 22 21:23:11 +0000 2016", "in_reply_to_status_id_str": null, "place": null, "extended_entities": {"media": [{"expanded_url": "https://twitter.com/marincuric/status/801174211595120644/photo/1", "display_url": "pic.twitter.com/X5BRQTDRm4", "url": "https://t.co/X5BRQTDRm4", "media_url_https": "https://pbs.twimg.com/media/Cx5XbbyXgAAhnVZ.jpg", "id_str": "801173912545624064", "sizes": {"large": {"h": 667, "resize": "fit", "w": 1351}, "small": {"h": 336, "resize": "fit", "w": 680}, "medium": {"h": 592, "resize": "fit", "w": 1200}, "thumb": {"h": 150, "resize": "crop", "w": 150}}, "indices": [93, 116], "type": "photo", "id": 801173912545624064, "media_url": "http://pbs.twimg.com/media/Cx5XbbyXgAAhnVZ.jpg"}]}, "metadata": {"iso_language_code": "en", "result_type": "recent"}}, {"contributors": null, "truncated": false, "text": "I'm finding it so hard to get into #TheGirlOnTheTrain because has Paula Hawkins EVER HEARD OF A COMMA SPLICE? It's like comma city over here", "is_quote_status": false, "in_reply_to_status_id": null, "id": 801174191043121152, "favorite_count": 0, "entities": {"symbols": [], "user_mentions": [], "hashtags": [{"indices": [35, 53], "text": "TheGirlOnTheTrain"}], "urls": []}, "retweeted": false, "coordinates": null, "source": "<a href=\"http://twitter.com/download/iphone\" rel=\"nofollow\">Twitter for iPhone</a>", "in_reply_to_screen_name": null, "in_reply_to_user_id": null, "retweet_count": 0, "id_str": "801174191043121152", "favorited": false, "user": {"follow_request_sent": false, "has_extended_profile": false, "profile_use_background_image": true, "default_profile_image": false, "id": 49395267, "profile_background_image_url_https": "https://pbs.twimg.com/profile_background_images/19200625/blackchandelier_background.jpg", "verified": false, "translator_type": "none", "profile_text_color": "333333", "profile_image_url_https": "https://pbs.twimg.com/profile_images/617918927478390784/gGwZ0Fnh_normal.jpg", "profile_sidebar_fill_color": "FFFFFF", "entities": {"url": {"urls": [{"url": "https://t.co/oEJckpztTj", "indices": [0, 23], "expanded_url": "http://www.bachplease.com", "display_url": "bachplease.com"}]}, "description": {"urls": []}}, "followers_count": 455, "profile_sidebar_border_color": "333333", "id_str": "49395267", "profile_background_color": "FFFFFF", "listed_count": 8, "is_translation_enabled": false, "utc_offset": -18000, "statuses_count": 11375, "description": "Life through a neon pink lens", "friends_count": 372, "location": "insta: @queenxchristine", "profile_link_color": "F5ABB5", "profile_image_url": "http://pbs.twimg.com/profile_images/617918927478390784/gGwZ0Fnh_normal.jpg", "following": false, "geo_enabled": false, "profile_banner_url": "https://pbs.twimg.com/profile_banners/49395267/1431315326", "profile_background_image_url": "http://pbs.twimg.com/profile_background_images/19200625/blackchandelier_background.jpg", "screen_name": "christine__liu", "lang": "en", "profile_background_tile": false, "favourites_count": 2162, "name": "Queen \u265b Christine", "notifications": false, "url": "https://t.co/oEJckpztTj", "created_at": "Sun Jun 21 19:02:00 +0000 2009", "contributors_enabled": false, "time_zone": "Quito", "protected": false, "default_profile": false, "is_translator": false}, "geo": null, "in_reply_to_user_id_str": null, "lang": "en", "created_at": "Tue Nov 22 21:23:06 +0000 2016", "in_reply_to_status_id_str": null, "place": null, "metadata": {"iso_language_code": "en", "result_type": "recent"}}, {"contributors": null, "truncated": false, "text": "Check out #TheGirlontheTrain by #PaulaHawkins https://t.co/sfmegtc9gc", "is_quote_status": false, "in_reply_to_status_id": null, "id": 801166389524529152, "favorite_count": 0, "entities": {"symbols": [], "user_mentions": [], "hashtags": [{"indices": [10, 28], "text": "TheGirlontheTrain"}, {"indices": [32, 45], "text": "PaulaHawkins"}], "urls": [{"url": "https://t.co/sfmegtc9gc", "indices": [46, 69], "expanded_url": "http://amzn.to/1UaVnyA", "display_url": "amzn.to/1UaVnyA"}]}, "retweeted": false, "coordinates": null, "source": "<a href=\"http://twitter.com\" rel=\"nofollow\">Twitter Web Client</a>", "in_reply_to_screen_name": null, "in_reply_to_user_id": null, "retweet_count": 0, "id_str": "801166389524529152", "favorited": false, "user": {"follow_request_sent": false, "has_extended_profile": false, "profile_use_background_image": true, "default_profile_image": false, "id": 4909252631, "profile_background_image_url_https": null, "verified": false, "translator_type": "none", "profile_text_color": "333333", "profile_image_url_https": "https://pbs.twimg.com/profile_images/698888608502177792/PHwDrjzq_normal.jpg", "profile_sidebar_fill_color": "DDEEF6", "entities": {"description": {"urls": []}}, "followers_count": 5068, "profile_sidebar_border_color": "C0DEED", "id_str": "4909252631", "profile_background_color": "F5F8FA", "listed_count": 124, "is_translation_enabled": false, "utc_offset": null, "statuses_count": 23992, "description": "#Kindle #Prizes & updates on the latest #books and #offers in the #UK", "friends_count": 4218, "location": "United Kingdom", "profile_link_color": "1DA1F2", "profile_image_url": "http://pbs.twimg.com/profile_images/698888608502177792/PHwDrjzq_normal.jpg", "following": false, "geo_enabled": false, "profile_banner_url": "https://pbs.twimg.com/profile_banners/4909252631/1455463381", "profile_background_image_url": null, "screen_name": "KindlePrizes", "lang": "en-gb", "profile_background_tile": false, "favourites_count": 1, "name": "Kindle Prizes", "notifications": false, "url": null, "created_at": "Sun Feb 14 14:54:13 +0000 2016", "contributors_enabled": false, "time_zone": null, "protected": false, "default_profile": true, "is_translator": false}, "geo": null, "in_reply_to_user_id_str": null, "possibly_sensitive": false, "lang": "en", "created_at": "Tue Nov 22 20:52:06 +0000 2016", "in_reply_to_status_id_str": null, "place": null, "metadata": {"iso_language_code": "en", "result_type": "recent"}}, {"contributors": null, "truncated": false, "text": "Was #TheGirlOnTheTrain a good movie ? #Ttm", "is_quote_status": false, "in_reply_to_status_id": null, "id": 801164235464146944, "favorite_count": 0, "entities": {"symbols": [], "user_mentions": [], "hashtags": [{"indices": [4, 22], "text": "TheGirlOnTheTrain"}, {"indices": [38, 42], "text": "Ttm"}], "urls": []}, "retweeted": false, "coordinates": null, "source": "<a href=\"http://twitter.com/download/iphone\" rel=\"nofollow\">Twitter for iPhone</a>", "in_reply_to_screen_name": null, "in_reply_to_user_id": null, "retweet_count": 0, "id_str": "801164235464146944", "favorited": false, "user": {"follow_request_sent": false, "has_extended_profile": true, "profile_use_background_image": false, "default_profile_image": false, "id": 243449962, "profile_background_image_url_https": "https://pbs.twimg.com/profile_background_images/611793858/l5uyxhq2610260im6zhj.jpeg", "verified": false, "translator_type": "none", "profile_text_color": "333333", "profile_image_url_https": "https://pbs.twimg.com/profile_images/799464614824177665/Ko6BzI_J_normal.jpg", "profile_sidebar_fill_color": "C0DFEC", "entities": {"description": {"urls": []}}, "followers_count": 2595, "profile_sidebar_border_color": "FFFFFF", "id_str": "243449962", "profile_background_color": "2F02EF", "listed_count": 1, "is_translation_enabled": false, "utc_offset": -18000, "statuses_count": 32280, "description": "I'm A Catfish ...Don't Dm Me \ud83d\udc8b| #CharssCreations\ud83d\udc9a| Interior Designer in the Making \ud83d\udc81\ud83c\udffd| A\ud83d\udc95\ud83d\udc8d", "friends_count": 2004, "location": "IUP", "profile_link_color": "19CF86", "profile_image_url": "http://pbs.twimg.com/profile_images/799464614824177665/Ko6BzI_J_normal.jpg", "following": false, "geo_enabled": true, "profile_banner_url": "https://pbs.twimg.com/profile_banners/243449962/1478926158", "profile_background_image_url": "http://pbs.twimg.com/profile_background_images/611793858/l5uyxhq2610260im6zhj.jpeg", "screen_name": "Avangiline_love", "lang": "en", "profile_background_tile": true, "favourites_count": 41, "name": "CharssCreations\ud83d\udc9a", "notifications": false, "url": null, "created_at": "Thu Jan 27 02:19:16 +0000 2011", "contributors_enabled": false, "time_zone": "America/New_York", "protected": false, "default_profile": false, "is_translator": false}, "geo": null, "in_reply_to_user_id_str": null, "lang": "en", "created_at": "Tue Nov 22 20:43:33 +0000 2016", "in_reply_to_status_id_str": null, "place": null, "metadata": {"iso_language_code": "en", "result_type": "recent"}}, {"contributors": null, "truncated": false, "text": "Leaving the station...\n#TheGirlOnTheTrain -- final show at the County is today at 8PM.\nhttps://t.co/dkNErOOkHC https://t.co/o6kqroI3l7", "is_quote_status": true, "in_reply_to_status_id": null, "id": 801159219315490816, "favorite_count": 0, "entities": {"symbols": [], "user_mentions": [], "hashtags": [{"indices": [23, 41], "text": "TheGirlOnTheTrain"}], "urls": [{"url": "https://t.co/dkNErOOkHC", "indices": [87, 110], "expanded_url": "http://www.countytheater.org/films/girl-on-the-train", "display_url": "countytheater.org/films/girl-on-\u2026"}, {"url": "https://t.co/o6kqroI3l7", "indices": [111, 134], "expanded_url": "https://twitter.com/thegirlontrain/status/735968648636960770", "display_url": "twitter.com/thegirlontrain\u2026"}]}, "quoted_status_id": 735968648636960770, "retweeted": false, "coordinates": null, "quoted_status": {"contributors": null, "truncated": false, "text": "One moment can change your life forever. In theaters October 7. https://t.co/h7wUopPvBA", "is_quote_status": false, "in_reply_to_status_id": null, "id": 735968648636960770, "favorite_count": 136, "entities": {"symbols": [], "user_mentions": [], "hashtags": [], "urls": [], "media": [{"expanded_url": "https://twitter.com/thegirlontrain/status/735968648636960770/photo/1", "display_url": "pic.twitter.com/h7wUopPvBA", "url": "https://t.co/h7wUopPvBA", "media_url_https": "https://pbs.twimg.com/media/CjavlgcUoAEu0lr.jpg", "id_str": "735968648020402177", "sizes": {"small": {"h": 170, "resize": "fit", "w": 340}, "large": {"h": 500, "resize": "fit", "w": 1000}, "medium": {"h": 300, "resize": "fit", "w": 600}, "thumb": {"h": 150, "resize": "crop", "w": 150}}, "indices": [64, 87], "type": "photo", "id": 735968648020402177, "media_url": "http://pbs.twimg.com/media/CjavlgcUoAEu0lr.jpg"}]}, "retweeted": false, "coordinates": null, "source": "<a href=\"http://twitter.com\" rel=\"nofollow\">Twitter Web Client</a>", "in_reply_to_screen_name": null, "in_reply_to_user_id": null, "retweet_count": 83, "id_str": "735968648636960770", "favorited": false, "user": {"follow_request_sent": false, "has_extended_profile": false, "profile_use_background_image": true, "default_profile_image": false, "id": 3884297806, "profile_background_image_url_https": "https://abs.twimg.com/images/themes/theme1/bg.png", "verified": true, "translator_type": "none", "profile_text_color": "333333", "profile_image_url_https": "https://pbs.twimg.com/profile_images/794606795419308032/0oo6p1MG_normal.jpg", "profile_sidebar_fill_color": "DDEEF6", "entities": {"url": {"urls": [{"url": "https://t.co/c0ussMotya", "indices": [0, 23], "expanded_url": "http://www.thegirlonthetrainmovie.com", "display_url": "thegirlonthetrainmovie.com"}]}, "description": {"urls": [{"url": "https://t.co/WYp8K1efCo", "indices": [104, 127], "expanded_url": "http://uni.pictures/TGOTT", "display_url": "uni.pictures/TGOTT"}]}}, "followers_count": 5261, "profile_sidebar_border_color": "C0DEED", "id_str": "3884297806", "profile_background_color": "C0DEED", "listed_count": 41, "is_translation_enabled": false, "utc_offset": null, "statuses_count": 72, "description": "The Girl On The Train, own it with Deleted and Extended Scenes on Digital HD 1/3 and Blu-ray & DVD 1/17 https://t.co/WYp8K1efCo", "friends_count": 17, "location": "", "profile_link_color": "1DA1F2", "profile_image_url": "http://pbs.twimg.com/profile_images/794606795419308032/0oo6p1MG_normal.jpg", "following": false, "geo_enabled": false, "profile_banner_url": "https://pbs.twimg.com/profile_banners/3884297806/1469216253", "profile_background_image_url": "http://abs.twimg.com/images/themes/theme1/bg.png", "screen_name": "thegirlontrain", "lang": "en", "profile_background_tile": false, "favourites_count": 24, "name": "#TheGirlOnTheTrain", "notifications": false, "url": "https://t.co/c0ussMotya", "created_at": "Tue Oct 06 21:55:51 +0000 2015", "contributors_enabled": false, "time_zone": null, "protected": false, "default_profile": true, "is_translator": false}, "geo": null, "in_reply_to_user_id_str": null, "possibly_sensitive": false, "lang": "en", "created_at": "Thu May 26 22:59:34 +0000 2016", "in_reply_to_status_id_str": null, "place": null, "extended_entities": {"media": [{"expanded_url": "https://twitter.com/thegirlontrain/status/735968648636960770/photo/1", "display_url": "pic.twitter.com/h7wUopPvBA", "url": "https://t.co/h7wUopPvBA", "media_url_https": "https://pbs.twimg.com/media/CjavlgcUoAEu0lr.jpg", "id_str": "735968648020402177", "sizes": {"small": {"h": 170, "resize": "fit", "w": 340}, "large": {"h": 500, "resize": "fit", "w": 1000}, "medium": {"h": 300, "resize": "fit", "w": 600}, "thumb": {"h": 150, "resize": "crop", "w": 150}}, "indices": [64, 87], "type": "photo", "id": 735968648020402177, "media_url": "http://pbs.twimg.com/media/CjavlgcUoAEu0lr.jpg"}]}, "metadata": {"iso_language_code": "en", "result_type": "recent"}}, "source": "<a href=\"http://twitter.com\" rel=\"nofollow\">Twitter Web Client</a>", "in_reply_to_screen_name": null, "in_reply_to_user_id": null, "retweet_count": 0, "id_str": "801159219315490816", "favorited": false, "user": {"follow_request_sent": false, "has_extended_profile": false, "profile_use_background_image": true, "default_profile_image": false, "id": 47826476, "profile_background_image_url_https": "https://pbs.twimg.com/profile_background_images/671635638/e393b385c4cb37cbb2f0cc3c30ae4d69.jpeg", "verified": false, "translator_type": "none", "profile_text_color": "666666", "profile_image_url_https": "https://pbs.twimg.com/profile_images/668872302096846848/-o4IJRrH_normal.png", "profile_sidebar_fill_color": "252429", "entities": {"url": {"urls": [{"url": "http://t.co/bR12YHS6NN", "indices": [0, 22], "expanded_url": "http://www.countytheater.org", "display_url": "countytheater.org"}]}, "description": {"urls": []}}, "followers_count": 2982, "profile_sidebar_border_color": "FFFFFF", "id_str": "47826476", "profile_background_color": "1A1B1F", "listed_count": 96, "is_translation_enabled": false, "utc_offset": -18000, "statuses_count": 5762, "description": "Providing great movies and events to the Doylestown community.", "friends_count": 179, "location": "Doylestown PA", "profile_link_color": "2FC2EF", "profile_image_url": "http://pbs.twimg.com/profile_images/668872302096846848/-o4IJRrH_normal.png", "following": false, "geo_enabled": true, "profile_banner_url": "https://pbs.twimg.com/profile_banners/47826476/1448307199", "profile_background_image_url": "http://pbs.twimg.com/profile_background_images/671635638/e393b385c4cb37cbb2f0cc3c30ae4d69.jpeg", "screen_name": "CountyTheater", "lang": "en", "profile_background_tile": false, "favourites_count": 241, "name": "County Theater", "notifications": false, "url": "http://t.co/bR12YHS6NN", "created_at": "Wed Jun 17 02:38:09 +0000 2009", "contributors_enabled": false, "time_zone": "Quito", "protected": false, "default_profile": false, "is_translator": false}, "geo": null, "in_reply_to_user_id_str": null, "possibly_sensitive": false, "lang": "en", "created_at": "Tue Nov 22 20:23:37 +0000 2016", "quoted_status_id_str": "735968648636960770", "in_reply_to_status_id_str": null, "place": null, "metadata": {"iso_language_code": "en", "result_type": "recent"}}, {"contributors": null, "truncated": true, "text": "It\u2019s CHEAP MOVIE #Tuesday \ud83d\udcb8 Now playing: \n#BleedForThis \ud83e\udd4a \n#EdgeOf17 \ud83d\udc81\n#TheGirlOnTheTrain \ud83d\ude82\n#Denial \ud83d\ude45\n#TheCarer \ud83d\udc9e\u2026 https://t.co/JIYaBWjmza", "is_quote_status": false, "in_reply_to_status_id": null, "id": 801157697920008192, "favorite_count": 1, "entities": {"symbols": [], "user_mentions": [], "hashtags": [{"indices": [17, 25], "text": "Tuesday"}, {"indices": [42, 55], "text": "BleedForThis"}, {"indices": [59, 68], "text": "EdgeOf17"}, {"indices": [71, 89], "text": "TheGirlOnTheTrain"}, {"indices": [92, 99], "text": "Denial"}, {"indices": [102, 111], "text": "TheCarer"}], "urls": [{"url": "https://t.co/JIYaBWjmza", "indices": [115, 138], "expanded_url": "https://twitter.com/i/web/status/801157697920008192", "display_url": "twitter.com/i/web/status/8\u2026"}]}, "retweeted": false, "coordinates": null, "source": "<a href=\"http://www.hootsuite.com\" rel=\"nofollow\">Hootsuite</a>", "in_reply_to_screen_name": null, "in_reply_to_user_id": null, "retweet_count": 0, "id_str": "801157697920008192", "favorited": false, "user": {"follow_request_sent": false, "has_extended_profile": false, "profile_use_background_image": true, "default_profile_image": false, "id": 150825267, "profile_background_image_url_https": "https://pbs.twimg.com/profile_background_images/169818250/twitter.jpg", "verified": false, "translator_type": "none", "profile_text_color": "333333", "profile_image_url_https": "https://pbs.twimg.com/profile_images/736697355030822912/AhPp3LQF_normal.jpg", "profile_sidebar_fill_color": "C0DFEC", "entities": {"url": {"urls": [{"url": "http://t.co/nVGn333J2S", "indices": [0, 22], "expanded_url": "http://www.carltoncinema.ca", "display_url": "carltoncinema.ca"}]}, "description": {"urls": []}}, "followers_count": 2553, "profile_sidebar_border_color": "A8C7F7", "id_str": "150825267", "profile_background_color": "022330", "listed_count": 112, "is_translation_enabled": false, "utc_offset": -18000, "statuses_count": 10687, "description": "Toronto's Premiere Indie Film Venue - 20 Carlton St. at Yonge", "friends_count": 493, "location": "Toronto, ON", "profile_link_color": "0084B4", "profile_image_url": "http://pbs.twimg.com/profile_images/736697355030822912/AhPp3LQF_normal.jpg", "following": false, "geo_enabled": false, "profile_banner_url": "https://pbs.twimg.com/profile_banners/150825267/1479621225", "profile_background_image_url": "http://pbs.twimg.com/profile_background_images/169818250/twitter.jpg", "screen_name": "ImagineCarlton", "lang": "en", "profile_background_tile": false, "favourites_count": 3231, "name": "Carlton Cinema", "notifications": false, "url": "http://t.co/nVGn333J2S", "created_at": "Tue Jun 01 22:56:10 +0000 2010", "contributors_enabled": false, "time_zone": "Eastern Time (US & Canada)", "protected": false, "default_profile": false, "is_translator": false}, "geo": null, "in_reply_to_user_id_str": null, "possibly_sensitive": false, "lang": "en", "created_at": "Tue Nov 22 20:17:34 +0000 2016", "in_reply_to_status_id_str": null, "place": null, "metadata": {"iso_language_code": "en", "result_type": "recent"}}, {"contributors": null, "truncated": false, "text": "RT @LukeEvans_News: Please keep supporting #TheGirlOnTheTrain and vote here https://t.co/BuA1kQZeh6 @thegirlontrain @girlontrainfilm https:\u2026", "is_quote_status": false, "in_reply_to_status_id": null, "id": 801155974761512960, "favorite_count": 0, "entities": {"symbols": [], "user_mentions": [{"id": 301769285, "indices": [3, 18], "id_str": "301769285", "screen_name": "LukeEvans_News", "name": "LukeEvans_News"}, {"id": 3884297806, "indices": [100, 115], "id_str": "3884297806", "screen_name": "thegirlontrain", "name": "#TheGirlOnTheTrain"}, {"id": 3684353896, "indices": [116, 132], "id_str": "3684353896", "screen_name": "girlontrainfilm", "name": "Girl on the Train"}], "hashtags": [{"indices": [43, 61], "text": "TheGirlOnTheTrain"}], "urls": [{"url": "https://t.co/BuA1kQZeh6", "indices": [76, 99], "expanded_url": "http://vote.peopleschoice.com/#!/home/all/15/1", "display_url": "vote.peopleschoice.com/#!/home/all/15\u2026"}]}, "retweeted": false, "coordinates": null, "source": "<a href=\"http://twitter.com/download/android\" rel=\"nofollow\">Twitter for Android</a>", "in_reply_to_screen_name": null, "in_reply_to_user_id": null, "retweet_count": 5, "id_str": "801155974761512960", "favorited": false, "retweeted_status": {"contributors": null, "truncated": false, "text": "Please keep supporting #TheGirlOnTheTrain and vote here https://t.co/BuA1kQZeh6 @thegirlontrain @girlontrainfilm https://t.co/yHIMm8LOtr", "is_quote_status": false, "in_reply_to_status_id": 800768518123712512, "id": 800821847629688832, "favorite_count": 3, "entities": {"symbols": [], "user_mentions": [{"id": 3884297806, "indices": [80, 95], "id_str": "3884297806", "screen_name": "thegirlontrain", "name": "#TheGirlOnTheTrain"}, {"id": 3684353896, "indices": [96, 112], "id_str": "3684353896", "screen_name": "girlontrainfilm", "name": "Girl on the Train"}], "hashtags": [{"indices": [23, 41], "text": "TheGirlOnTheTrain"}], "urls": [{"url": "https://t.co/BuA1kQZeh6", "indices": [56, 79], "expanded_url": "http://vote.peopleschoice.com/#!/home/all/15/1", "display_url": "vote.peopleschoice.com/#!/home/all/15\u2026"}], "media": [{"expanded_url": "https://twitter.com/LukeEvans_News/status/800821847629688832/photo/1", "display_url": "pic.twitter.com/yHIMm8LOtr", "url": "https://t.co/yHIMm8LOtr", "media_url_https": "https://pbs.twimg.com/media/Cx0XOJ2XgAAwiUo.jpg", "id_str": "800821840671375360", "sizes": {"large": {"h": 1593, "resize": "fit", "w": 1242}, "small": {"h": 680, "resize": "fit", "w": 530}, "medium": {"h": 1200, "resize": "fit", "w": 936}, "thumb": {"h": 150, "resize": "crop", "w": 150}}, "indices": [113, 136], "type": "photo", "id": 800821840671375360, "media_url": "http://pbs.twimg.com/media/Cx0XOJ2XgAAwiUo.jpg"}]}, "retweeted": false, "coordinates": null, "source": "<a href=\"http://twitter.com/download/iphone\" rel=\"nofollow\">Twitter for iPhone</a>", "in_reply_to_screen_name": "thegirlontrain", "in_reply_to_user_id": 3884297806, "retweet_count": 5, "id_str": "800821847629688832", "favorited": false, "user": {"follow_request_sent": false, "has_extended_profile": false, "profile_use_background_image": true, "default_profile_image": false, "id": 301769285, "profile_background_image_url_https": "https://pbs.twimg.com/profile_background_images/585875277009391616/ZieU97Gn.jpg", "verified": false, "translator_type": "none", "profile_text_color": "BD6D0B", "profile_image_url_https": "https://pbs.twimg.com/profile_images/789424973962240001/4QxtvK5-_normal.jpg", "profile_sidebar_fill_color": "DDEEF6", "entities": {"url": {"urls": [{"url": "https://t.co/bwHc79nSK0", "indices": [0, 23], "expanded_url": "http://twitpic.com/photos/LukeEvans_News", "display_url": "twitpic.com/photos/LukeEva\u2026"}]}, "description": {"urls": []}}, "followers_count": 3329, "profile_sidebar_border_color": "FFFFFF", "id_str": "301769285", "profile_background_color": "383638", "listed_count": 114, "is_translation_enabled": false, "utc_offset": -18000, "statuses_count": 29782, "description": "Follow the latest news about Luke Evans! One of the most exciting actors of this generation! Elle Award and GQ Bond Winner! Sexiest Welshman! ( We are not Luke)", "friends_count": 295, "location": "Whosay World Exlorer Winner ", "profile_link_color": "3B94D9", "profile_image_url": "http://pbs.twimg.com/profile_images/789424973962240001/4QxtvK5-_normal.jpg", "following": false, "geo_enabled": false, "profile_banner_url": "https://pbs.twimg.com/profile_banners/301769285/1476205046", "profile_background_image_url": "http://pbs.twimg.com/profile_background_images/585875277009391616/ZieU97Gn.jpg", "screen_name": "LukeEvans_News", "lang": "en", "profile_background_tile": true, "favourites_count": 10802, "name": "LukeEvans_News", "notifications": false, "url": "https://t.co/bwHc79nSK0", "created_at": "Fri May 20 01:22:50 +0000 2011", "contributors_enabled": false, "time_zone": "Eastern Time (US & Canada)", "protected": false, "default_profile": false, "is_translator": false}, "geo": null, "in_reply_to_user_id_str": "3884297806", "possibly_sensitive": false, "lang": "en", "created_at": "Mon Nov 21 22:03:01 +0000 2016", "in_reply_to_status_id_str": "800768518123712512", "place": null, "extended_entities": {"media": [{"expanded_url": "https://twitter.com/LukeEvans_News/status/800821847629688832/photo/1", "display_url": "pic.twitter.com/yHIMm8LOtr", "url": "https://t.co/yHIMm8LOtr", "media_url_https": "https://pbs.twimg.com/media/Cx0XOJ2XgAAwiUo.jpg", "id_str": "800821840671375360", "sizes": {"large": {"h": 1593, "resize": "fit", "w": 1242}, "small": {"h": 680, "resize": "fit", "w": 530}, "medium": {"h": 1200, "resize": "fit", "w": 936}, "thumb": {"h": 150, "resize": "crop", "w": 150}}, "indices": [113, 136], "type": "photo", "id": 800821840671375360, "media_url": "http://pbs.twimg.com/media/Cx0XOJ2XgAAwiUo.jpg"}]}, "metadata": {"iso_language_code": "en", "result_type": "recent"}}, "user": {"follow_request_sent": false, "has_extended_profile": true, "profile_use_background_image": true, "default_profile_image": false, "id": 335810499, "profile_background_image_url_https": "https://pbs.twimg.com/profile_background_images/378800000062132596/bbe87e2cd5ddd84a9f93bb5c508c811c.jpeg", "verified": false, "translator_type": "none", "profile_text_color": "666666", "profile_image_url_https": "https://pbs.twimg.com/profile_images/768048829312696320/uQaNszj0_normal.jpg", "profile_sidebar_fill_color": "252429", "entities": {"description": {"urls": []}}, "followers_count": 442, "profile_sidebar_border_color": "FFFFFF", "id_str": "335810499", "profile_background_color": "F7F9FF", "listed_count": 13, "is_translation_enabled": false, "utc_offset": -10800, "statuses_count": 7925, "description": "#LukeEvans, I'm a Luketeer,\n\nTotally into TV-Series like #ChicagoFire, #GreysAnatomy, #NCIS or #CriminalMinds", "friends_count": 627, "location": "Duisburg, Germany", "profile_link_color": "206D85", "profile_image_url": "http://pbs.twimg.com/profile_images/768048829312696320/uQaNszj0_normal.jpg", "following": false, "geo_enabled": false, "profile_banner_url": "https://pbs.twimg.com/profile_banners/335810499/1478943048", "profile_background_image_url": "http://pbs.twimg.com/profile_background_images/378800000062132596/bbe87e2cd5ddd84a9f93bb5c508c811c.jpeg", "screen_name": "manu_262", "lang": "de", "profile_background_tile": true, "favourites_count": 2547, "name": "manu s.", "notifications": false, "url": null, "created_at": "Fri Jul 15 08:22:33 +0000 2011", "contributors_enabled": false, "time_zone": "Greenland", "protected": false, "default_profile": false, "is_translator": false}, "geo": null, "in_reply_to_user_id_str": null, "possibly_sensitive": false, "lang": "en", "created_at": "Tue Nov 22 20:10:43 +0000 2016", "in_reply_to_status_id_str": null, "place": null, "metadata": {"iso_language_code": "en", "result_type": "recent"}}]